octoprint_dashboard/__init__.py
octoprint_dashboard/app.py
octoprint_dashboard/cli_commands.py
octoprint_dashboard/config.py
octoprint_dashboard/api/__init__.py
octoprint_dashboard/api/api.py
octoprint_dashboard/api/config.py
octoprint_dashboard/api/decorators.py
octoprint_dashboard/api/file.py
octoprint_dashboard/api/group.py
octoprint_dashboard/api/groupSettings.py
octoprint_dashboard/api/localOctoPrintService.py
octoprint_dashboard/api/printer.py
octoprint_dashboard/api/printerSettings.py
octoprint_dashboard/api/printerStatus.py
octoprint_dashboard/api/superadmin.py
octoprint_dashboard/api/user.py
octoprint_dashboard/background/OctoprintStatus.py
octoprint_dashboard/background/ZeroconfBrowser.py
octoprint_dashboard/background/__init__.py
octoprint_dashboard/dist/app-2d2d50dc0e4098fa60f2.js
octoprint_dashboard/dist/app-55d267ee34fa934d6666.js
octoprint_dashboard/dist/app-8b36910b009b84c82aa0.js
octoprint_dashboard/dist/index.html
octoprint_dashboard/dist/vendor-2d2d50dc0e4098fa60f2.js
octoprint_dashboard/dist/vendor-55d267ee34fa934d6666.js
octoprint_dashboard/dist/vendor-8b36910b009b84c82aa0.js
octoprint_dashboard/login/__init__.py
octoprint_dashboard/login/decorators.py
octoprint_dashboard/login/routes.py
octoprint_dashboard/model/Config.py
octoprint_dashboard/model/Group.py
octoprint_dashboard/model/GroupUser.py
octoprint_dashboard/model/Printer.py
octoprint_dashboard/model/User.py
octoprint_dashboard/model/__init__.py
octoprint_dashboard/model/utils.py
octoprint_dashboard/model/migrations/README
octoprint_dashboard/model/migrations/__init__.py
octoprint_dashboard/model/migrations/alembic.ini
octoprint_dashboard/model/migrations/env.py
octoprint_dashboard/model/migrations/script.py.mako
octoprint_dashboard/model/migrations/__pycache__/env.cpython-36.pyc
octoprint_dashboard/model/migrations/versions/573d726a5860_.py
octoprint_dashboard/model/migrations/versions/cbe89e18a65d_.py
octoprint_dashboard-0.3.3.dist-info/DESCRIPTION.rst
octoprint_dashboard-0.3.3.dist-info/METADATA
octoprint_dashboard-0.3.3.dist-info/RECORD
octoprint_dashboard-0.3.3.dist-info/WHEEL
octoprint_dashboard-0.3.3.dist-info/metadata.json
octoprint_dashboard-0.3.3.dist-info/top_level.txt
