Metadata-Version: 2.0
Name: octoprint-dashboard
Version: 0.3.3
Summary: Runs server application for controlling multiple 3D printers with OctoPrint
Home-page: https://github.com/meadowfrey/OctoPrint-Dashboard
Author: Jiří Makarius
Author-email: UNKNOWN
License: MIT
Keywords: octoprint 3Dprint dashboard python flask
Platform: UNKNOWN
Classifier: Development Status :: 3 - Alpha
Classifier: Environment :: Web Environment
Classifier: Framework :: Flask
Classifier: Intended Audience :: Science/Research
Classifier: Intended Audience :: Manufacturing
Classifier: Intended Audience :: End Users/Desktop
Classifier: Intended Audience :: Information Technology
Classifier: License :: OSI Approved :: MIT License
Classifier: Operating System :: POSIX :: Linux
Classifier: Programming Language :: Python
Classifier: Programming Language :: Python :: 3 :: Only
Classifier: Programming Language :: Python :: 3.5
Classifier: Programming Language :: Python :: 3.6
Classifier: Programming Language :: JavaScript
Classifier: Programming Language :: Python :: Implementation :: PyPy
Classifier: Topic :: Internet :: WWW/HTTP :: WSGI
Classifier: Topic :: Printing
Classifier: Topic :: System :: Networking :: Monitoring
Requires-Dist: alembic
Requires-Dist: eventlet
Requires-Dist: flask
Requires-Dist: flask-cors
Requires-Dist: flask-migrate
Requires-Dist: flask-restful
Requires-Dist: flask-socketio
Requires-Dist: flask-sqlalchemy
Requires-Dist: octoclient
Requires-Dist: pyjwt
Requires-Dist: raven[flask]
Requires-Dist: requests
Requires-Dist: zeroconf
